azure/mgmt/storagediscovery/__init__.py
azure/mgmt/storagediscovery/_client.py
azure/mgmt/storagediscovery/_configuration.py
azure/mgmt/storagediscovery/_patch.py
azure/mgmt/storagediscovery/_version.py
azure/mgmt/storagediscovery/py.typed
azure/mgmt/storagediscovery/_utils/__init__.py
azure/mgmt/storagediscovery/_utils/model_base.py
azure/mgmt/storagediscovery/_utils/serialization.py
azure/mgmt/storagediscovery/aio/__init__.py
azure/mgmt/storagediscovery/aio/_client.py
azure/mgmt/storagediscovery/aio/_configuration.py
azure/mgmt/storagediscovery/aio/_patch.py
azure/mgmt/storagediscovery/aio/operations/__init__.py
azure/mgmt/storagediscovery/aio/operations/_operations.py
azure/mgmt/storagediscovery/aio/operations/_patch.py
azure/mgmt/storagediscovery/models/__init__.py
azure/mgmt/storagediscovery/models/_enums.py
azure/mgmt/storagediscovery/models/_models.py
azure/mgmt/storagediscovery/models/_patch.py
azure/mgmt/storagediscovery/operations/__init__.py
azure/mgmt/storagediscovery/operations/_operations.py
azure/mgmt/storagediscovery/operations/_patch.py
azure_mgmt_storagediscovery-1.0.1.dist-info/licenses/LICENSE
azure_mgmt_storagediscovery-1.0.1.dist-info/METADATA
azure_mgmt_storagediscovery-1.0.1.dist-info/WHEEL
azure_mgmt_storagediscovery-1.0.1.dist-info/top_level.txt
azure_mgmt_storagediscovery-1.0.1.dist-info/RECORD
